<Functions>
  <Function Name="Match">
    <Setting Key="Match_RemoveTimelines" SpName="Match_RemoveTimelines" DbName="DefaultConnection" />
    <Setting Key="Match_GetByDateRange" SpName="Match_GetByDateRange" DbName="DefaultConnection" />

    <Setting Key="Match_InsertOrUpdatePostMatches" SpName="Match_InsertOrUpdatePostMatches" DbName="DefaultConnection" />
    <Setting Key="Match_InsertOrUpdatePostMatches_Former" SpName="Match_InsertOrUpdatePostMatches" DbName="FormerDbConnection" />
    <Setting Key="Match_InsertOrUpdatePostMatches_Ahead" SpName="Match_InsertOrUpdatePostMatches" DbName="AheadDbConnection" />

    <Setting Key="Match_InsertMatches" SpName="Match_InsertMatches" DbName="DefaultConnection" />
    <Setting Key="Match_InsertMatches_Former" SpName="Match_InsertMatches" DbName="FormerDbConnection" />
    <Setting Key="Match_InsertMatches_Ahead" SpName="Match_InsertMatches" DbName="AheadDbConnection" />

    <Setting Key="Match_InsertTimeline" SpName="Match_InsertTimeline" DbName="DefaultConnection" />
    <Setting Key="Match_InsertTimeline_Former" SpName="Match_InsertTimeline" DbName="FormerDbConnection" />
    <Setting Key="Match_InsertTimeline_Ahead" SpName="Match_InsertTimeline" DbName="AheadDbConnection" />

    <Setting Key="Match_GetTimelineEvents" SpName="Match_GetTimelineEvents" DbName="DefaultConnection" />
    <Setting Key="Match_GetTimelineEvents_Former" SpName="Match_GetTimelineEvents" DbName="FormerDbConnection" />
    <Setting Key="Match_GetTimelineEvents_Ahead" SpName="Match_GetTimelineEvents" DbName="AheadDbConnection" />

    <Setting Key="Match_UpdateRefereeAndAttendance" SpName="Match_UpdateRefereeAndAttendance" DbName="DefaultConnection" />
    <Setting Key="Match_UpdateRefereeAndAttendance_Former" SpName="Match_UpdateRefereeAndAttendance" DbName="FormerDbConnection" />
    <Setting Key="Match_UpdateRefereeAndAttendance_Ahead" SpName="Match_UpdateRefereeAndAttendance" DbName="AheadDbConnection" />

    <Setting Key="Match_GetById" SpName="Match_GetById" DbName="DefaultConnection" />
    <Setting Key="Match_GetById_Former" SpName="Match_GetById" DbName="FormerDbConnection" />
    <Setting Key="Match_GetById_Ahead" SpName="Match_GetById" DbName="AheadDbConnection" />

    <Setting Key="Match_UpdateCoverage" SpName="Match_UpdateCoverage" DbName="DefaultConnection" />
    <Setting Key="Match_UpdateCoverage_Former" SpName="Match_UpdateCoverage" DbName="FormerDbConnection" />
    <Setting Key="Match_UpdateCoverage_Ahead" SpName="Match_UpdateCoverage" DbName="AheadDbConnection" />

    <Setting Key="Match_InsertCommentary" SpName="Match_InsertCommentary" DbName="DefaultConnection" />
    <Setting Key="Match_InsertCommentary_Former" SpName="Match_InsertCommentary" DbName="FormerDbConnection" />
    <Setting Key="Match_InsertCommentary_Ahead" SpName="Match_InsertCommentary" DbName="AheadDbConnection" />

    <Setting Key="Match_InsertOrUpdateLineups" SpName="Match_InsertOrUpdateLineups" DbName="DefaultConnection" />
    <Setting Key="Match_InsertOrUpdateLineups_Former" SpName="Match_InsertOrUpdateLineups" DbName="FormerDbConnection" />
    <Setting Key="Match_InsertOrUpdateLineups_Ahead" SpName="Match_InsertOrUpdateLineups" DbName="AheadDbConnection" />
  </Function>
  <Function Name="LiveMatch">
    <Setting Key="LiveMatch_UpdateCurrentPeriodStartTime" SpName="LiveMatch_UpdateCurrentPeriodStartTime" DbName="DefaultConnection" />
    <Setting Key="LiveMatch_GetBySportId" SpName="LiveMatch_GetBySportId" DbName="DefaultConnection" />
    <Setting Key="LiveMatch_InsertOrRemove" SpName="LiveMatch_InsertOrRemove" DbName="DefaultConnection" />

    <Setting Key="LiveMatch_UpdateMatchResult" SpName="LiveMatch_UpdateMatchResult" DbName="DefaultConnection" />
    <Setting Key="LiveMatch_UpdateMatchResult_Former" SpName="LiveMatch_UpdateMatchResult" DbName="FormerDbConnection" />
    <Setting Key="LiveMatch_UpdateMatchResult_Ahead" SpName="LiveMatch_UpdateMatchResult" DbName="AheadDbConnection" />

    <Setting Key="LiveMatch_UpdateLastTimeline" SpName="LiveMatch_UpdateLastTimeline" DbName="DefaultConnection" />
    <Setting Key="LiveMatch_UpdateLastTimeline_Former" SpName="LiveMatch_UpdateLastTimeline" DbName="FormerDbConnection" />
    <Setting Key="LiveMatch_UpdateLastTimeline_Ahead" SpName="LiveMatch_UpdateLastTimeline" DbName="AheadDbConnection" />

    <Setting Key="LiveMatch_UpdateTeamStatistic" SpName="LiveMatch_UpdateTeamStatistic" DbName="DefaultConnection" />
    <Setting Key="LiveMatch_UpdateTeamStatistic_Former" SpName="LiveMatch_UpdateTeamStatistic" DbName="FormerDbConnection" />
    <Setting Key="LiveMatch_UpdateTeamStatistic_Ahead" SpName="LiveMatch_UpdateTeamStatistic" DbName="AheadDbConnection" />

    <Setting Key="LiveMatch_UpdateTeamCards" SpName="LiveMatch_UpdateTeamCards" DbName="DefaultConnection" />
    <Setting Key="LiveMatch_UpdateTeamCards_Former" SpName="LiveMatch_UpdateTeamCards" DbName="FormerDbConnection" />
    <Setting Key="LiveMatch_UpdateTeamCards_Ahead" SpName="LiveMatch_UpdateTeamCards" DbName="AheadDbConnection" />

    <Setting Key="LiveMatch_UpdateInjuryTime" SpName="LiveMatch_UpdateInjuryTime" DbName="DefaultConnection" />
    <Setting Key="LiveMatch_UpdateInjuryTime_Former" SpName="LiveMatch_UpdateInjuryTime" DbName="FormerDbConnection" />
    <Setting Key="LiveMatch_UpdateInjuryTime_Ahead" SpName="LiveMatch_UpdateInjuryTime" DbName="AheadDbConnection" />
  </Function>
  <Function Name="Odds">
    <Setting Key="Odds_InsertOdds" SpName="Odds_InsertOdds" DbName="DefaultConnection" />
    <Setting Key="Odds_InsertOdds_Former" SpName="Odds_InsertOdds" DbName="FormerDbConnection" />
    <Setting Key="Odds_InsertOdds_Ahead" SpName="Odds_InsertOdds" DbName="AheadDbConnection" />

    <Setting Key="Odds_GetOdds" SpName="Odds_GetOdds" DbName="DefaultConnection" />
    <Setting Key="Odds_GetOdds_Former" SpName="Odds_GetOdds" DbName="FormerDbConnection" />
    <Setting Key="Odds_GetOdds_Ahead" SpName="Odds_GetOdds" DbName="AheadDbConnection" />
  </Function>
  <Function Name="League">
    <Setting Key="League_GetActive" SpName="League_GetActive" DbName="DefaultConnection" />
    <Setting Key="League_InsertInternationalLeagues" SpName="League_InsertInternationalLeagues" DbName="DefaultConnection" />
    <Setting Key="League_InsertCountryLeagues" SpName="League_InsertCountryLeagues" DbName="DefaultConnection" />
    <Setting Key="League_InsertLeagueSeason" SpName="League_InsertLeagueSeason" DbName="DefaultConnection" />
    <Setting Key="League_InsertOrUpdateStandings" SpName="League_InsertOrUpdateStandings" DbName="DefaultConnection" />
    <Setting Key="League_GetStandings" SpName="League_GetStandings" DbName="DefaultConnection" />
    <Setting Key="League_UpdateFetchedLeagueSeason" SpName="League_UpdateFetchedLeagueSeason" DbName="DefaultConnection" />
    <Setting Key="League_UpdateCurrentSeason" SpName="League_UpdateCurrentSeason" DbName="DefaultConnection" />
    <Setting Key="League_InsertGroupStage" SpName="League_InsertGroupStage" DbName="DefaultConnection" />
    <Setting Key="League_UpdateGroupHasStanding" SpName="League_UpdateGroupHasStanding" DbName="DefaultConnection" />
    <Setting Key="League_EnableHasGroups" SpName="League_EnableHasGroups" DbName="DefaultConnection" />
  </Function>
  <Function Name="Team">
    <Setting Key="Team_InsertOrUpdateHeadToHead" SpName="Team_InsertOrUpdateHeadToHead" DbName="DefaultConnection" />
    <Setting Key="Team_InsertOrUpdate" SpName="Team_InsertOrUpdate" DbName="DefaultConnection" />
  </Function>
  <Function Name="News">
    <Setting Key="News_InsertOrUpdateNews" SpName="News_InsertOrUpdateNews" DbName="DefaultConnection" />
    <Setting Key="News_InsertOrUpdateImage" SpName="News_InsertOrUpdateImage" DbName="DefaultConnection" />
  </Function>
  <Function Name="Favorites">
    <Setting Key="UserFavorite_GetUsersByFavoriteId" SpName="UserFavorite_GetUsersByFavoriteId" DbName="DefaultConnection" />
  </Function>
</Functions>